setup.py
mypackage_rachelhan.egg-info/PKG-INFO
mypackage_rachelhan.egg-info/SOURCES.txt
mypackage_rachelhan.egg-info/dependency_links.txt
mypackage_rachelhan.egg-info/top_level.txt
mypackagehan/__init__.py