Metadata-Version: 1.0
Name: mypackage-rachelhan
Version: 0.1
Summary: This is the desc.
Home-page: UNKNOWN
Author: UNKNOWN
Author-email: UNKNOWN
License: Apache License, Version 2.0
Platform: UNKNOWN
